{
  "id": "t10-683",
  "notes": [
    {
      "term": "浮云",
      "def": "喻游子飘游不定。游子：此指李白。"
    },
    {
      "term": "这两句说",
      "def": "李白一连三夜入我梦中，足见对我情亲意厚。这也是从对方设想的写法。"
    },
    {
      "term": "告归",
      "def": "辞别。"
    },
    {
      "term": "局促",
      "def": "短促，匆促。"
    },
    {
      "term": "搔首",
      "def": "大概是李白不如意时的习惯举动。"
    },
    {
      "term": "冠",
      "def": "官帽。盖：车上的篷盖。冠盖：指代达官。斯人：此人，指李白。"
    },
    {
      "term": "孰云",
      "def": "谁说。网恢恢：《老子》有“天网恢恢，疏而不漏”的话。此处指法网恢恢。这句意思是：谁说天网宽疏，对你却过于严酷了。"
    },
    {
      "term": "这两句说",
      "def": "他活着的时候虽然寂寞困苦，但必将获得千秋万岁的声名。"
    }
  ],
  "translation": [
    "天上浮云终日飞来飘去，远游的故人为何久久不至。",
    "夜晚我总是频频梦到你，可知你对我的深情厚谊。",
    "分别时你总是神色匆匆，还总说相见多不容易。",
    "江湖上航行多险风恶浪，担心你的船被掀翻沉没。",
    "出门时搔着满头的白发，悔恨辜负自己平生之志。",
    "京都的官僚们冠盖相续，才华盖世的你却容颜憔悴。",
    "谁能说天理公道无欺人，迟暮之年却无辜受牵累。",
    "即使有流芳千秋的美名，难以补偿遭受的冷落悲戚。"
  ],
  "appreciation": [
    "《梦李白二首·其二》是一首记梦诗。此诗描写梦中所见李白的形象，抒写对老友悲惨遭遇的同情。诗中前四句写诗人三夜频梦李白，抒写对故人的一片衷情；“告归” 以下六句，写梦中李白魂返前的幻影，其形可见，声可闻，情可触，李白枯槁惨淡之状，历历在目；“冠盖” 以下六句，是写诗人梦醒后为李白的遭遇坎坷表示不平之意，也饱含着自己坎坷零落的无限心事。全诗形象鲜明，结构完整，情感真诚，体现了李杜两人形离神合、肝胆相照、互劝互勉、至情交往的友谊。"
  ],
  "background": [
    "《梦李白二首》是乾元二年（759年）秋杜甫流寓秦州时所作，此诗为其中一首。至德二载（757年），李白因曾参与永王李璘的幕府受到牵连，下狱浔阳（今江西九江）。乾元元年（758年）初，又被定罪长流夜郎（今贵州桐梓）。乾元二年（759年）二月，在三峡流放途中，遇赦放还，回到江陵。杜甫这时流寓秦州，地方僻远，消息隔绝，只闻李白流放，不知已被赦还，仍在为李白忧虑，作此二诗以寄意。"
  ],
  "source": "gushiwen-web"
}
