{
  "id": "t29-607",
  "notes": [
    {
      "term": "茂陵",
      "def": "陵墓名。汉武帝陵墓，在今陕西兴平县东北。"
    },
    {
      "term": "天马",
      "def": "骏马。"
    },
    {
      "term": "蒲梢",
      "def": "古代骏马名。"
    },
    {
      "term": "苜蓿",
      "def": "豆科植物，原产新疆一带，因大宛马嗜食，汉武帝遣使采其种子遍植于离宫旁。"
    },
    {
      "term": "榴花",
      "def": "石榴花。"
    },
    {
      "term": "内苑",
      "def": "内宫，诗里指宫中侍从。"
    },
    {
      "term": "凤嘴",
      "def": "胶泥的名称。传说煮凤嘴、麟角作胶泥，可粘合弓弩刀剑的断裂处。"
    },
    {
      "term": "属车",
      "def": "皇帝侍从的座车。"
    },
    {
      "term": "鸡翘",
      "def": "皇帝出巡时，属车上插有用羽毛装饰的旗，百姓称之为“鸡翘”。"
    },
    {
      "term": "玉桃",
      "def": "传说人吃了可长生不老的仙桃。"
    },
    {
      "term": "方朔",
      "def": "东方朔，汉武帝时文人。"
    },
    {
      "term": "阿娇",
      "def": "汉武帝陈皇后的小名。传武帝年幼时曾说，如得阿娇为妻，将筑金屋以藏之。"
    },
    {
      "term": "苏卿",
      "def": "苏武，字子卿，武帝时出使匈奴，被扣留十九年，回国时武帝已死。"
    }
  ],
  "translation": [
    "汉家王室的蒲梢良马，由王室培育而成；长安近郊之上，苜蓿与石榴成片遍布。",
    "内苑中人整日只顾游猎，帝车为便于出行、掩人耳目，已不再插设鸡翘旗。",
    "曾被怜惜的，有偷得玉桃的东方朔，亦有被汉武帝藏于金屋的阿娇。",
    "谁曾想，滞留匈奴十九载才得以归国的苏武，奉旨拜谒茂陵时，唯见松柏矗立，细雨潇潇。"
  ],
  "appreciation": [
    "《茂陵》是一首七言律诗。诗的首联以骏马赞扬汉武帝之武功；中间两联写汉武帝好声色、求神仙、恋女色，以体现其欲望颇多；尾联谓苏武年老归国，武帝已逝，拜谒陵寝，风雨凄凄。这首诗综合使用传统的赋、比、兴手法，借咏汉武帝的功过，在象征和隐寓中抒发了诗人对唐武宗影射式的批评，句句用事、字斟句酌，个个到位，达到典丽、凝练、形象、隽永的艺术高度。"
  ],
  "background": [
    "此诗是李商隐结束各处幕府飘泊，晚年梓幕罢归返京经茂陵时所作，其时约为公元856年（大中十年）归抵长安，任盐铁推官前。"
  ],
  "source": "gushiwen-web"
}
