{
  "id": "t4-280",
  "notes": [
    {
      "term": "军",
      "def": "指军中。"
    },
    {
      "term": "风威",
      "def": "军威。"
    },
    {
      "term": "冷",
      "def": "望而生畏的意思。"
    },
    {
      "term": "水气",
      "def": "指杀气。"
    },
    {
      "term": "寒",
      "def": "不寒而栗。"
    },
    {
      "term": "戎衣",
      "def": "即军装。"
    },
    {
      "term": "定",
      "def": "平定。"
    },
    {
      "term": "歌舞",
      "def": "载歌载舞。"
    },
    {
      "term": "长安",
      "def": "唐的都城。"
    }
  ],
  "translation": [
    "城上军威使人望而生畏，连江中的水都似乎杀气腾腾。",
    "现在，我身穿军装准备战斗，等到平定了天下时，一定载歌载舞进入长安京城。"
  ],
  "appreciation": [
    "诗歌以对句起兴，在深秋的一个清晨，诗人登上了广陵城楼，纵目远望，浮思遐想。此刻楼高风急，江雾浓重，风雨潇潇。“城上风威冷，江中水气寒”两句写深秋景色,城上冷风飕飕，江中水气寒冷，好一派肃杀景象。诗句晓畅隽永，看似质朴平易不着笔力。诗人借用了《梁书·元帝纪》中“信与江水同流，气与寒风共愤”的典故，恰到好处地抒发了同仇敌忾的豪情与激愤。充分表现临战前的紧张、肃穆、庄严的气氛和将士们的进取、希望和信心。此二句营造一个“风冷水寒”的悲剧氛围，与“风潇潇兮易水寒”一样，给人以慷慨悲壮苍凉激越的感受。诗的三四句写诗人对讨武战争必胜的信心。第三句诗“戎衣何日定”，“何日”意为“总有一天”，以否定式表肯定，必胜之心力透纸背。这句诗借周武王讨伐殷纣王的故事隐喻李敬业讨伐武则天是以有道伐无道，说明“匡复”是正义的，顺应民心、天意的，因此也必定是会胜利的。诗的最后一句，“歌舞入长安”，水到渠成轻松自然地作了结尾，表现出诗人必胜的信念及勇往直前，不成功则成仁的彻底反抗精神和大无畏气概。",
    "这首诗工于用典且浑然一体，增强了诗的深度和概括力。这首小诗，属对工整，语言朴实，音韵和谐流畅。若将此诗的意境分而析之，不难发现，此诗所描述的是“风冷水寒”的清冷之境，而“戎衣歌舞”所体现的却是诗人的满腔热情和雄心，这一“冷”一“热”对比，映衬，赋予了此诗特有的魅力。",
    "《在军登城楼》是一首五言绝句。该诗以对句起兴，写在深秋的一个清晨，诗人登上了广陵城楼，纵目远望，浮思遐想，然后写他对讨武战争必胜的信心。此诗工于用典且浑然一体，增强了诗的深度和概括力，其属对工整、语言朴实、音韵和谐流畅，一“冷”一“热”的对比赋予了它独特的魅力。"
  ],
  "background": [
    "公元684年，光宅元年，唐高宗去世，武则天把持朝政，引起人民不满。不久被贬为柳州司马的李敬业（本名徐敬业）提出“匡复唐室”的口号，在扬州起兵征讨武则天。被贬为临海丞的骆宾王也投奔李敬业麾下，负责军中宣传工作。《在军登城楼》与《讨武曌檄》作于同一时期。"
  ],
  "source": "gushiwen-web"
}
