{
  "id": "t49-879",
  "notes": [
    {
      "term": "弄珠拾翠",
      "def": "语出曹植《洛神赋》：“或采明珠，或拾翠羽。”拾翠：拾取翠鸟羽毛以为首饰。后以指妇女嬉游的景象。"
    },
    {
      "term": "盈盈",
      "def": "仪态美好貌。"
    },
    {
      "term": "兰桡",
      "def": "小舟的美称。"
    },
    {
      "term": "采莲调",
      "def": "采莲子，词调名。"
    },
    {
      "term": "交颈",
      "def": "颈与颈相互依摩。多为雌雄动物之间的一种亲昵表示。"
    }
  ],
  "translation": [
    "满眼都是秋日风光。风清气爽，露水洁白，莲花红艳，流水碧绿。是从哪里的梦中醒来？恍惚间似见采拾珠翠的娇美身影，倚在船边，眉头轻轻蹙着。",
    "采莲的歌声平稳悠扬，吴地同伴的歌声接连不断，靠着船桨在吴江的曲折处停留。傍晚的天空中白鹭飞起，几对相互依偎的鸳鸯，钻进芦花深处栖息。"
  ],
  "appreciation": [
    "词的上片写秋光满目，展现了一幅绚烂多彩的秋日画卷，再引出“佳人”的形象，奠定了清新而又略带忧郁的情感基调；下片转而描写采莲的场景，展现了江南水乡的宁静与和谐。整首词笔触细腻，将人与自然的和谐共处表现得淋漓尽致，同时也寄托了词人对宁静、美好生活的向往之情。"
  ],
  "background": [],
  "source": "gushiwen-web"
}
