{"slug":"廖融","name":"廖融","dynasty":"唐","style":"字元素","life":"","origin":"","seal":"廖","bio":["廖融，字元素，隐居衡山。诗七首。"],"works":[{"id":"t42-586","title":"谢翁宏以诗百篇见示","kind":"诗"},{"id":"t42-587","title":"赠天台逸人","kind":"诗"},{"id":"t42-588","title":"古桧","kind":"诗"},{"id":"t42-589","title":"题伍彬屋壁","kind":"诗"},{"id":"t42-590","title":"梦仙谣","kind":"诗"},{"id":"t42-591","title":"退宫妓","kind":"诗"},{"id":"t42-592","title":"句","kind":"诗"},{"id":"t55-970","title":"赠王正己（题拟）","kind":"诗"},{"id":"t55-971","title":"赠狄涣","kind":"诗"}]}