{"slug":"晁采","name":"晁采","dynasty":"唐","style":"字试莺","life":"","origin":"","seal":"晁","bio":["晁采，小字试莺，大历时人，少与邻生文茂约为伉俪。及长，茂时寄诗通情，采以莲子达意，坠一于盆，逾旬，开花并蒂。茂以报采，乘间欢合。","母得其情，叹曰：“才子佳人，自应有此。”遂以采归茂。诗二十二首。"],"works":[{"id":"t43-979","title":"寄文茂","kind":"诗"},{"id":"t43-980","title":"秋日再寄","kind":"诗"},{"id":"t43-981","title":"春日送夫之长安","kind":"诗"},{"id":"t43-982","title":"雨中忆夫 一","kind":"诗"},{"id":"t43-983","title":"雨中忆夫 二","kind":"诗"},{"id":"t43-984","title":"子夜歌十八首 一","kind":"诗"},{"id":"t43-985","title":"子夜歌十八首 二","kind":"诗"},{"id":"t43-986","title":"子夜歌十八首 三","kind":"诗"},{"id":"t43-987","title":"子夜歌十八首 四","kind":"诗"},{"id":"t43-988","title":"子夜歌十八首 五","kind":"诗"},{"id":"t43-989","title":"子夜歌十八首 六","kind":"诗"},{"id":"t43-990","title":"子夜歌十八首 七","kind":"诗"},{"id":"t43-991","title":"子夜歌十八首 八","kind":"诗"},{"id":"t43-992","title":"子夜歌十八首 九","kind":"诗"},{"id":"t43-993","title":"子夜歌十八首 十","kind":"诗"},{"id":"t43-994","title":"子夜歌十八首 十一","kind":"诗"},{"id":"t43-995","title":"子夜歌十八首 十二","kind":"诗"},{"id":"t43-996","title":"子夜歌十八首 十三","kind":"诗"},{"id":"t43-997","title":"子夜歌十八首 十四","kind":"诗"},{"id":"t43-998","title":"子夜歌十八首 十五","kind":"诗"},{"id":"t43-999","title":"子夜歌十八首 十六","kind":"诗"},{"id":"t44-0","title":"子夜歌十八首 十七","kind":"诗"},{"id":"t44-1","title":"子夜歌十八首 十八","kind":"诗"}]}