{"slug":"韩元吉","name":"韩元吉","dynasty":"宋","style":"字无咎 · 号南涧","life":"","origin":"许昌（今属河南）","seal":"韩","bio":["--(1118－1187) 字无咎，号南涧，许昌 (今属河南) 人，徙居信州上饶 (今属江西)。韩维四世孙。吕祖谦之外舅。","官至吏部尚书。曾与张元、张孝祥、范成大、陆游、辛弃疾等以词唱和，风调亦近辛派。著有《南涧甲乙稿》、《南涧诗馀》。"],"works":[{"id":"c66-388","title":"点绛唇·木落霜浓","kind":"词"},{"id":"c66-389","title":"浣溪沙·莫惜清尊领客同","kind":"词"},{"id":"c66-390","title":"霜天晓角·倚天绝壁","kind":"词"},{"id":"c66-391","title":"霜天晓角·几声残角","kind":"词"},{"id":"c66-392","title":"菩萨蛮·春残日日风和雨","kind":"词"},{"id":"c66-393","title":"菩萨蛮·江南雪里花如玉","kind":"词"},{"id":"c66-394","title":"菩萨蛮·薄云卷雨凉成阵","kind":"词"},{"id":"c66-395","title":"菩萨蛮·诏书昨夜先春到","kind":"词"},{"id":"c66-396","title":"菩萨蛮·墙根新笋看成竹","kind":"词"},{"id":"c66-397","title":"菩萨蛮·梧桐叶上秋萧瑟","kind":"词"},{"id":"c66-398","title":"减字木兰花·壶中春早","kind":"词"},{"id":"c66-399","title":"减字木兰花·风梳雨洗","kind":"词"},{"id":"c66-400","title":"诉衷情·疏疏密密未开时","kind":"词"},{"id":"c66-401","title":"谒金门·春尚浅","kind":"词"},{"id":"c66-402","title":"谒金门·幽槛暑","kind":"词"},{"id":"c66-403","title":"好事近·华屋翠云深","kind":"词"},{"id":"c66-404","title":"好事近·秋意满芙蓉","kind":"词"},{"id":"c66-405","title":"秦楼月・忆秦娥·莺声寂","kind":"词"},{"id":"c66-406","title":"朝中措·危亭崛起卧苍龙","kind":"词"},{"id":"c66-407","title":"贺圣朝·斜阳只向花梢驻","kind":"词"},{"id":"c66-408","title":"西江月·一度难逢佳节","kind":"词"},{"id":"c66-409","title":"西江月·山路冥冥雨暗","kind":"词"},{"id":"c66-410","title":"燕归梁·凉月圆时翠帐深","kind":"词"},{"id":"c66-411","title":"南柯子・南歌子·急雨朝来过","kind":"词"},{"id":"c66-412","title":"南柯子・南歌子·野杏抟枝熟","kind":"词"},{"id":"c66-413","title":"浪淘沙·席地赏残红","kind":"词"},{"id":"c66-414","title":"浪淘沙·倦客怕离歌","kind":"词"},{"id":"c66-415","title":"浪淘沙·鶗鴂怨花残","kind":"词"},{"id":"c66-416","title":"鹧鸪天·山绕江城腊又残","kind":"词"},{"id":"c66-417","title":"鹧鸪天·不惜黄花插满头","kind":"词"},{"id":"c66-418","title":"鹧鸪天·老去休惊节物催","kind":"词"},{"id":"c66-419","title":"虞美人·西风斜日兰皋路","kind":"词"},{"id":"c66-420","title":"虞美人·登临自古骚人事","kind":"词"},{"id":"c66-421","title":"虞美人·烟霄脉脉停机杼","kind":"词"},{"id":"c66-422","title":"虞美人·诏书昨夜催春到","kind":"词"},{"id":"c66-423","title":"夜行船·极目高亭横远岫","kind":"词"},{"id":"c66-424","title":"南乡子·江路木犀天","kind":"词"},{"id":"c66-425","title":"南乡子·细雨弄中秋","kind":"词"},{"id":"c66-426","title":"醉落魄・一斛珠·楼头晚鼓","kind":"词"},{"id":"c66-427","title":"醉落魄・一斛珠·菊花又折","kind":"词"},{"id":"c66-428","title":"一翦梅·竹里疏枝总是梅","kind":"词"},{"id":"c66-429","title":"临江仙·记得年时离别夜","kind":"词"},{"id":"c66-430","title":"临江仙·自古文章贤太守","kind":"词"},{"id":"c66-431","title":"江神子・江城子·十年此地看花时","kind":"词"},{"id":"c66-432","title":"江神子・江城子·金银楼阁认蓬莱","kind":"词"},{"id":"c66-433","title":"满江红·梅欲开时","kind":"词"},{"id":"c66-434","title":"满江红·寂寞山城","kind":"词"},{"id":"c66-435","title":"满江红·江绕层城","kind":"词"},{"id":"c66-436","title":"水调歌头·世事不须问","kind":"词"},{"id":"c66-437","title":"水调歌头·江路晓来雨","kind":"词"}]}