[{"id":"t5-600","title":"桃花溪","rhythmic":null,"author":"张旭","authorSlug":"张旭","dynasty":"唐","kind":"shi","paragraphs":["隐隐飞桥隔野烟，石矶西畔问渔船。","桃花尽日随流水，洞在清溪何处边。"]},{"id":"t5-601","title":"山行留客","rhythmic":null,"author":"张旭","authorSlug":"张旭","dynasty":"唐","kind":"shi","paragraphs":["山光物态弄春辉，莫为轻阴便拟归。","纵使晴明无雨色，入云深处亦沾衣。"]},{"id":"t5-602","title":"春游值雨","rhythmic":null,"author":"张旭","authorSlug":"张旭","dynasty":"唐","kind":"shi","paragraphs":["欲寻轩槛列清尊，江上烟云向晚昏。","须倩东风吹散雨，明朝却待入华园。"]},{"id":"t5-603","title":"春草","rhythmic":null,"author":"张旭","authorSlug":"张旭","dynasty":"唐","kind":"shi","paragraphs":["春草青青万里余，边城落日见离居。","情知海上三年别，不寄云间一纸书。"]},{"id":"t5-604","title":"柳","rhythmic":null,"author":"张旭","authorSlug":"张旭","dynasty":"唐","kind":"shi","paragraphs":["濯濯烟条拂地垂，城边楼畔结春思。","请君细看风流意，未减灵和殿里时。"]},{"id":"t5-605","title":"南山","rhythmic":null,"author":"贺朝","authorSlug":"贺朝","dynasty":"唐","kind":"shi","paragraphs":["湖北雨初晴，湖南山尽见。","岩岩石帆影，如得海风便。","仙穴茅山峰，彩云时一见。","邀君共探此，异箓残几卷。"]},{"id":"t5-606","title":"孤兴","rhythmic":null,"author":"贺朝","authorSlug":"贺朝","dynasty":"唐","kind":"shi","paragraphs":["晴日暖珠箔，夭桃色正新。","红粉青镜中，娟娟可怜嚬。","君子在遐险，蕙心谁见珍。","罗幕空掩昼，玉颜静移春。","江瑟语幽独，再三情未申。","黄鹄千里翅，芳音迟所因。"]},{"id":"t5-607","title":"从军行","rhythmic":null,"author":"贺朝","authorSlug":"贺朝","dynasty":"唐","kind":"shi","paragraphs":["朔胡乘月寇边城，军书插羽刺中京。","天子金坛拜飞将，单于玉塞振佳兵。","骑射先鸣推任侠，龙韬决胜伫时英。","闻有河湟客，愔愔理帷帟。","常山启霸图，汜水先天策。","衔珠浴铁向桑干，衅旗膏劒指乌丸。","鸣鸡已报关山晓，来雁遥传沙塞寒。","直为甘心从苦节，陇头流水鸣呜咽。","边树萧萧不觉春，天山漠漠长飞雪。","鱼丽阵接塞云平，雁翼营通海月明。","始看晋幕飞鹅入，旋闻齐垒啼乌声。","自从一戍燕支山，春光几度晋阳关。","金河未转青丝骑，玉筯应啼红粉颜。","鸿归燕相续，池边芳草绿。","已见氛清细柳营，莫更春歌落梅曲。","烽沈灶减静边亭，海[晏]山空肃已宁。","行望凤京旋凯捷，重来麟阁画丹青。"]},{"id":"t5-608","title":"赋得游人久不归","rhythmic":null,"author":"贺朝","authorSlug":"贺朝","dynasty":"唐","kind":"shi","paragraphs":["乡关眇天末，引领怅怀归。","羇旅久淫滞，物色屡芳菲。","稍觉出意尽，行看蓬鬓稀。","如何千里外，伫立沾裳衣。"]},{"id":"t5-609","title":"宿香山阁","rhythmic":null,"author":"贺朝","authorSlug":"贺朝","dynasty":"唐","kind":"shi","paragraphs":["暝上春山阁，梯云宿半空。","轩窗闭潮海，枕席拂烟虹。","朱网防栖鸽，纱灯护夕虫。","一闻鸡唱晓，已见日曈曈。"]},{"id":"t5-610","title":"赠酒店胡姬","rhythmic":null,"author":"贺朝","authorSlug":"贺朝","dynasty":"唐","kind":"shi","paragraphs":["胡姬春酒店，弦管夜锵锵。","红毾铺新月，貂裘坐薄霜。","玉盘初鲙鲤，金鼎正烹羊。","上客无劳散，听歌乐世娘。"]},{"id":"t5-611","title":"赋得春莺送友人二首 一","rhythmic":null,"author":"贺朝","authorSlug":"贺朝","dynasty":"唐","kind":"shi","paragraphs":["翅掩飞莺舞，啼恼婕妤悲。","料取金闺意，因君问所思。"]},{"id":"t5-612","title":"赋得春莺送友人二首 二","rhythmic":null,"author":"贺朝","authorSlug":"贺朝","dynasty":"唐","kind":"shi","paragraphs":["流莺拂绣羽，二月上林期。","待雪销金禁，衔花向玉墀。"]},{"id":"t5-613","title":"三日绿潭篇","rhythmic":null,"author":"万齐融","authorSlug":"万齐融","dynasty":"唐","kind":"shi","paragraphs":["春潭滉漾接隋宫，宫阙连延潭水东。","苹苔嫩色涵波绿，桃李新花照底红。","垂菱布藻如妆镜，丽日晴天相照暎。","素影沈沈对蝶飞，金沙砾砾窥鱼泳。","佳人祓禊赏韶年，倾国倾城并可怜。","拾翠总来芳树下，踏青争遶绿潭边。","公子王孙恣游玩，沙阳水曲情无厌。","禽浮似挹羽觞杯，鳞跃疑投水心劒。","金鞍玉勒骋轻肥，落絮红尘拥路飞。","绿水残霞催席散，画楼初月待人归。"]},{"id":"t5-614","title":"仗劒行","rhythmic":null,"author":"万齐融","authorSlug":"万齐融","dynasty":"唐","kind":"shi","paragraphs":["昨夜星官动紫微，今年天子用武威。","登车一呼风雷动，遥震阴山撼巍巍。","胡骄子，当见旄头蚀应死。","愿骑单马仗天威，挼取长绳缚虏归。","仗劒遥叱路傍子，匈奴头血溅君衣。"]},{"id":"t5-615","title":"赠别江头","rhythmic":null,"author":"万齐融","authorSlug":"万齐融","dynasty":"唐","kind":"shi","paragraphs":["东南飞鸟处，言是故乡天。","江上风花晚，君行定几千。","计程频破月，数别屡开年。","明岁浔阳水，相思寄采莲。"]},{"id":"t5-616","title":"送陈七还广陵","rhythmic":null,"author":"万齐融","authorSlug":"万齐融","dynasty":"唐","kind":"shi","paragraphs":["风流谁代子，虽有旧无双。","欢酒言相送，愁弦意不降。","落花馥河道，垂杨拂水窗。","海潮与春梦，朝夕广陵江。"]},{"id":"t5-617","title":"游春","rhythmic":null,"author":"邢巨","authorSlug":"邢巨","dynasty":"唐","kind":"shi","paragraphs":["海岳三峰古，春皇二月寒。","绿潭渔子钓，红树美人攀。","弱蔓环沙屿，飞花点石关。","溪山游未厌，琴酌弄晴湾。"]},{"id":"t5-618","title":"游宣州琴溪同武平一作","rhythmic":null,"author":"邢巨","authorSlug":"邢巨","dynasty":"唐","kind":"shi","paragraphs":["灵溪非人迹，仙意素所秉。","鳞岭森翠微，澄潭照秋景。"]},{"id":"t5-619","title":"春江花月夜","rhythmic":null,"author":"张若虚","authorSlug":"张若虚","dynasty":"唐","kind":"shi","paragraphs":["春江潮水连海平，海上明月共潮生。","滟滟随波千万里，何处春江无月明？","江流宛转遶芳甸，月照花林皆似霰。","空里流霜不觉飞，汀上白沙看不见。","江天一色无纤尘，皎皎空中孤月轮。","江畔何人初见月，江月何年初照人？","人生代代无穷已，江月年年秖相似。","不知江月待何人？但见长江送流水。","白云一片去悠悠，青枫浦上不胜愁。","谁家今夜扁舟子，何处相思明月楼？","可怜楼上月裴回，应照离人妆镜台。","玉户帘中卷不去，捣衣砧上拂还来。","此时相望不相闻，愿逐月华流照君。","鸿雁长飞光不度，鱼龙潜跃水成文。","昨夜闲潭梦落花，可怜春半不还家。","江水流春去欲尽，江潭落月复西斜。","斜月沈沈藏海雾，碣石潇湘无限路。","不知乘月几人归，落月摇情满江树。"]},{"id":"t5-620","title":"代答闺梦还","rhythmic":null,"author":"张若虚","authorSlug":"张若虚","dynasty":"唐","kind":"shi","paragraphs":["关塞年华早，楼台别望违。","试衫著煖气，开镜觅春晖。","燕入窥罗幕，蜂来上画衣。","情催桃李艳，心寄管弦飞。","妆洗朝相待，风花暝不归。","梦魂何处入，寂寂掩重扉。"]},{"id":"t5-621","title":"洪州客舍寄柳博士芳","rhythmic":null,"author":"薛业","authorSlug":"薛业","dynasty":"唐","kind":"shi","paragraphs":["去年燕巢主人屋，今年花发路傍枝。","年年为客不到舍，旧国存亡那得知。"]},{"id":"t5-622","title":"晚秋赠张折冲","rhythmic":null,"author":"薛业","authorSlug":"薛业","dynasty":"唐","kind":"shi","paragraphs":["都尉今无事，时清但闭关。","夜霜戎马瘦，秋草射堂闲。","位以穿杨得，名因折桂还。","冯唐真不遇，叹息鬓毛斑。"]},{"id":"t5-623","title":"和左司张员外自洛使入京中路先赴长安逢立春日赠韦侍御等诸公","rhythmic":null,"author":"孙逖","authorSlug":"孙逖","dynasty":"唐","kind":"shi","paragraphs":["拜郎登省闼，奉使驰车乘。","遥瞻使者星，便是郎官应。","台妙时相许，皇华德弥称。","二陕听风谣，三秦望形胜。","此中暌益友，是日多诗兴。","寒尽岁阴催，春归物华证。"]},{"id":"t5-624","title":"和登会稽山","rhythmic":null,"author":"孙逖","authorSlug":"孙逖","dynasty":"唐","kind":"shi","paragraphs":["稽山碧湖上，势入东溟尽。","烟景昼清明，九峰争隐嶙。","望中厌朱绂，俗内探玄牝。","野老听鸣驺，山童拥行轸。","仙花寒未落，古蔓柔堪引。","竹磵入山多，松崖向天近。","云从海天去，日就江村陨。","能赋丘尝闻，和歌参不敏。","冥搜信冲漠，多士期标准。","愿奉濯缨心，长谣反招隐。"]},{"id":"t5-625","title":"送杨法曹按括州","rhythmic":null,"author":"孙逖","authorSlug":"孙逖","dynasty":"唐","kind":"shi","paragraphs":["东海天台山，南方缙云驿。","溪澄问人隐，岩险烦登陟。","潭壑随星使，轩车绕春色。","傥寻琪树人，为报长相忆。"]},{"id":"t5-626","title":"葛山潭","rhythmic":null,"author":"孙逖","authorSlug":"孙逖","dynasty":"唐","kind":"shi","paragraphs":["圆潭写流月，晴明涵万象。","仙翁何时还，绿水空荡漾。","凉哉草木腓，白露沾人衣。","犹醉空山里，时闻笙鹤飞。"]},{"id":"t5-627","title":"丹阳行","rhythmic":null,"author":"孙逖","authorSlug":"孙逖","dynasty":"唐","kind":"shi","paragraphs":["丹阳古郡洞庭阴，落日扁舟此路寻。","传是东南旧都处，金陵中断碧江深。","在昔风尘起，京都乱如毁。","双阙戎虏间，千门战场里。","传闻一马化为龙，南渡衣冠亦愿从。","石头横帝里，京口拒戎锋。","青枫林下回天跸，杜若洲前转国容。","都门不见河阳树，辇道唯闻建业钟。","中原悠悠几千里，欲扫欃枪未云已。","英雄倾夺何纷然，一盛一衰如逝川。","可怜宫观重江里，金镜相传三百年。","自从龙见圣人出，六合车书混为一。","昔年王气今何在，并向长安就尧日。","荆榛古木闭荒阡，共道繁华不复全。","赤县唯余江树月，黄图半入海人烟。","暮来山水登临遍，览古愁吟泪如霰。","唯有空城多白云，春风淡荡无人见。"]},{"id":"t5-628","title":"山阴县西楼","rhythmic":null,"author":"孙逖","authorSlug":"孙逖","dynasty":"唐","kind":"shi","paragraphs":["都邑西楼芳树间，逶迤霁色遶江山。","山月夜从公署出，江云晚对讼庭还。","谁知春色朝朝好，二月飞花满江草。","一见湖边杨柳风，遥忆青青洛阳道。"]},{"id":"t5-629","title":"夜宿浙江","rhythmic":null,"author":"孙逖","authorSlug":"孙逖","dynasty":"唐","kind":"shi","paragraphs":["扁舟夜入江潭泊，露白风高气萧索。","富春渚上潮未还，天姥岑边月初落。","烟水茫茫多苦辛，更闻江上越人吟。","洛阳城阙何时见，西北浮云朝暝深。"]},{"id":"t5-630","title":"春日留别","rhythmic":null,"author":"孙逖","authorSlug":"孙逖","dynasty":"唐","kind":"shi","paragraphs":["春路逶迤花柳前，孤舟晚泊就人烟。","东山白云不可见，西陵江月夜娟娟。","春江夜尽潮声度，征帆遥从此中去。","越国山川看渐无，可怜愁思江南树。"]},{"id":"t5-631","title":"奉和四月三日上阳水窗赐宴应制得春字","rhythmic":null,"author":"孙逖","authorSlug":"孙逖","dynasty":"唐","kind":"shi","paragraphs":["今日逢初夏，欢游续旧旬。","气和先作雨，恩厚别成春。","凤吹临清洛，龙舆下紫宸。","此中歌在藻，还见跃潜鳞。"]},{"id":"t5-632","title":"奉和登会昌山应制","rhythmic":null,"author":"孙逖","authorSlug":"孙逖","dynasty":"唐","kind":"shi","paragraphs":["岩磴列云旗，吾君访道时。","干行万物覩，日驭六龙迟。","望远回天顾，登高动睿词。","愿因山作寿，长保会昌期。"]},{"id":"t5-633","title":"正月十五日夜应制","rhythmic":null,"author":"孙逖","authorSlug":"孙逖","dynasty":"唐","kind":"shi","paragraphs":["洛城三五夜，天子万年春。","彩仗移双阙，琼筵会九宾。","舞成苍颉字，灯作法王轮。","不觉东方日，遥垂御藻新。"]},{"id":"t5-634","title":"奉和御制登鸳鸯楼即目应制","rhythmic":null,"author":"孙逖","authorSlug":"孙逖","dynasty":"唐","kind":"shi","paragraphs":["玉辇下离宫，琼楼上半空。","方巡五年狩，更辟四门聪。","井邑观秦野，山河念禹功。","停銮留睿作，轩槛起南风。"]},{"id":"t5-635","title":"进船泛洛水应制","rhythmic":null,"author":"孙逖","authorSlug":"孙逖","dynasty":"唐","kind":"shi","paragraphs":["禁园纡睿览，仙櫂叶时游。","洛北风花树，江南彩画舟。","芳生兰蕙草，春入凤凰楼。","兴尽离宫暮，烟光起夕流。"]},{"id":"t5-636","title":"和常州崔使君寒食夜","rhythmic":null,"author":"孙逖","authorSlug":"孙逖","dynasty":"唐","kind":"shi","paragraphs":["闻道清明近，春庭向夕阑。","行游昼不厌，风物夜宜看。","斗柄更初转，梅香暗里残。","无劳秉华烛，清月在南端。"]},{"id":"t5-637","title":"和韦兄春日南亭宴兄弟","rhythmic":null,"author":"孙逖","authorSlug":"孙逖","dynasty":"唐","kind":"shi","paragraphs":["台阁升高位，园林隔旧乡。","忽闻歌棣萼，还比报琼芳。","门向宜春近，郊连御宿长。","德星常有会，相望在文昌。"]},{"id":"t5-638","title":"奉和崔司马游云门寺","rhythmic":null,"author":"孙逖","authorSlug":"孙逖","dynasty":"唐","kind":"shi","paragraphs":["系马清溪树，禅门春气浓。","香台花下出，讲坐竹间逢。","觉路山童引，经行谷鸟从。","更言穷寂灭，回策上南峰。"]},{"id":"t5-639","title":"酬万八贺九云门下归溪中作","rhythmic":null,"author":"孙逖","authorSlug":"孙逖","dynasty":"唐","kind":"shi","paragraphs":["晚从灵境出，林壑曙云飞。","稍觉清溪尽，回瞻画刹微。","独园余兴在，孤櫂宿心违。","更忆登攀处，天香满袖归。"]},{"id":"t5-640","title":"春初送吕补阙往西岳勒碑得云字","rhythmic":null,"author":"孙逖","authorSlug":"孙逖","dynasty":"唐","kind":"shi","paragraphs":["刻石记天文，朝推谷子云。","箧中缄圣札，岩下揖神君。","语别梅初艳，为期草欲薰。","往来春不尽，离思莫氛氲。"]},{"id":"t5-641","title":"送越州裴参军充使入京","rhythmic":null,"author":"孙逖","authorSlug":"孙逖","dynasty":"唐","kind":"shi","paragraphs":["日落川径寒，离心苦未安。","客愁西向尽，乡梦北归难。","霜果林中变，秋花水上残。","明朝渡江后，云物向南看。"]},{"id":"t5-642","title":"送周判官往台州","rhythmic":null,"author":"孙逖","authorSlug":"孙逖","dynasty":"唐","kind":"shi","paragraphs":["吾宗长作赋，登陆访天台。","星使行看入，云仙意转催。","饮冰攀璀璨，驱传历莓苔。","日暮东郊别，真情去不回。"]},{"id":"t5-643","title":"送魏骑曹充宇文侍御判官分按山南","rhythmic":null,"author":"孙逖","authorSlug":"孙逖","dynasty":"唐","kind":"shi","paragraphs":["云雨阳台路，光华驿骑巡。","劝农开梦土，恤隐惠荆人。","楼迥吟黄鹤，江长望白苹。","观风布明诏，更是汉南春。"]},{"id":"t5-644","title":"送苏郎中绾出佐荆州","rhythmic":null,"author":"孙逖","authorSlug":"孙逖","dynasty":"唐","kind":"shi","paragraphs":["神仙久留滞，清切伫飞翻。","忽佐南方牧，何时西掖垣。","高车自兰省，便道出荆门。","不见河梁别，空销郢路魂。"]},{"id":"t5-645","title":"冬末送魏起居赴京","rhythmic":null,"author":"孙逖","authorSlug":"孙逖","dynasty":"唐","kind":"shi","paragraphs":["大名将起魏，良史更逢迁。","驿骑朝丹阙，关亭望紫烟。","西京春色近，东观物华偏。","早赴王正月，挥毫记首年。"]},{"id":"t5-646","title":"送李补阙摄御史充河西节度判官","rhythmic":null,"author":"孙逖","authorSlug":"孙逖","dynasty":"唐","kind":"shi","paragraphs":["昔年叨补衮，边地亦埋轮。","官序慙先达，才名畏后人。","西戎虽献款，上策耻和亲。","早赴前军幕，长清外域尘。"]},{"id":"t5-647","title":"送赵评事摄御史监军岭南","rhythmic":null,"author":"孙逖","authorSlug":"孙逖","dynasty":"唐","kind":"shi","paragraphs":["议狱持邦典，临戎假宪威。","风从阊阖去，霜入洞庭飞。","篁竹迎金鼓，楼船引绣衣。","明年拜真月，南斗使星归。"]},{"id":"t5-648","title":"送靳十五侍御使蜀","rhythmic":null,"author":"孙逖","authorSlug":"孙逖","dynasty":"唐","kind":"shi","paragraphs":["天使出霜台，行人择吏才。","传车春色送，离兴夕阳催。","驿遶巴江转，关迎劒道开。","西南一何幸，前后二龙来。"]},{"id":"t5-649","title":"送李给事归徐州觐省","rhythmic":null,"author":"孙逖","authorSlug":"孙逖","dynasty":"唐","kind":"shi","paragraphs":["列位登青琐，还乡复彩衣。","共言晨省日，便是昼游归。","春水经梁宋，晴山入海沂。","莫愁东路远，四牡正𬴂𬴂。"]},{"id":"t5-650","title":"送杜侍御赴上都","rhythmic":null,"author":"孙逖","authorSlug":"孙逖","dynasty":"唐","kind":"shi","paragraphs":["避马台中贵，登车岭外遥。","还因贡赋礼，来谒大明朝。","地入商山路，乡连渭水桥。","承恩返南越，尊酒重相邀。"]},{"id":"t5-651","title":"送张环摄御史监南选","rhythmic":null,"author":"孙逖","authorSlug":"孙逖","dynasty":"唐","kind":"shi","paragraphs":["汉使得张纲，威名摄远方。","恩沾柱下史，荣比选曹郎。","江带黔中阔，山连峡水长。","莫愁炎暑地，秋至有严霜。"]},{"id":"t5-652","title":"宴越府陈法曹西亭","rhythmic":null,"author":"孙逖","authorSlug":"孙逖","dynasty":"唐","kind":"shi","paragraphs":["公府西岩下，红亭间白云。","雪梅初度腊，烟竹稍迎曛。","水木涵澄景，帘栊引霁氛。","江南归思逼，春鴈不堪闻。"]},{"id":"t5-653","title":"同邢判官寻龙湍观归湖中","rhythmic":null,"author":"孙逖","authorSlug":"孙逖","dynasty":"唐","kind":"shi","paragraphs":["星使下仙京，云湖喜昼晴。","更从探穴处，还作櫂歌行。","丝管荷风入，帘帷竹气清。","莫愁归路远，水月夜虚明。"]},{"id":"t5-654","title":"寻龙湍","rhythmic":null,"author":"孙逖","authorSlug":"孙逖","dynasty":"唐","kind":"shi","paragraphs":["仙穴寻遗迹，轻舟爱水乡。","溪流一曲尽，山路九峰长。","渔父歌金洞，江妃舞翠房。","遥怜葛仙宅，真气共微茫。"]},{"id":"t5-655","title":"宿云门寺阁","rhythmic":null,"author":"孙逖","authorSlug":"孙逖","dynasty":"唐","kind":"shi","paragraphs":["香阁东山下，烟花象外幽。","悬灯千嶂夕，卷幔五湖秋。","画壁余鸿鴈，纱窓宿斗牛。","更疑天路近，梦与白云游。"]},{"id":"t5-656","title":"扬子江楼","rhythmic":null,"author":"孙逖","authorSlug":"孙逖","dynasty":"唐","kind":"shi","paragraphs":["扬子何年邑，雄图作楚关。","江连二妃渚，云近八公山。","驿道[青]枫外，人烟绿屿间。","晚来潮正满，数处落帆还。"]},{"id":"t5-657","title":"淮阴夜宿二首 一","rhythmic":null,"author":"孙逖","authorSlug":"孙逖","dynasty":"唐","kind":"shi","paragraphs":["水国南无畔，扁舟北未期。","乡情淮上失，归梦郢中疑。","木落知寒近，山长见日迟。","客行心绪乱，不及洛阳时。"]},{"id":"t5-658","title":"淮阴夜宿二首 二","rhythmic":null,"author":"孙逖","authorSlug":"孙逖","dynasty":"唐","kind":"shi","paragraphs":["永夕卧烟塘，萧条天一方。","秋风淮水落，寒夜楚歌长。","宿莽非中土，鲈鱼岂我乡。","孤舟行已倦，南越尚茫茫。"]},{"id":"t5-659","title":"下京口埭夜行","rhythmic":null,"author":"孙逖","authorSlug":"孙逖","dynasty":"唐","kind":"shi","paragraphs":["孤帆度绿氛，寒浦落红曛。","江树朝来出，吴歌夜渐闻。","南溟接潮水，北斗近乡云。","行役从兹去，归情入鴈群。"]},{"id":"t5-660","title":"山行遇雨","rhythmic":null,"author":"孙逖","authorSlug":"孙逖","dynasty":"唐","kind":"shi","paragraphs":["骤雨昼氤氲，空天望不分。","暗山唯觉电，穷海但生云。","涉涧猜行潦，缘崖畏宿氛。","夜来江月霁，櫂唱此中闻。"]},{"id":"t5-661","title":"夜到润州","rhythmic":null,"author":"孙逖","authorSlug":"孙逖","dynasty":"唐","kind":"shi","paragraphs":["夜入丹阳郡，天高气象秋。","海隅云汉转，江畔火星流。","城郭传金柝，闾阎闭绿洲。","客行凡几夜，新月再如钩。"]},{"id":"t5-662","title":"和常州崔使君咏后庭梅二首 一","rhythmic":null,"author":"孙逖","authorSlug":"孙逖","dynasty":"唐","kind":"shi","paragraphs":["闻唱梅花落，江南春意深。","更传千里外，来入越人吟。","弱干红妆倚，繁香翠羽寻。","庭中自公日，歌舞向芳阴。"]},{"id":"t5-663","title":"和常州崔使君咏后庭梅二首 二","rhythmic":null,"author":"孙逖","authorSlug":"孙逖","dynasty":"唐","kind":"shi","paragraphs":["梅院重门掩，遥遥歌吹边。","庭深人不见，春至曲能传。","花落弹棋处，香来荐枕前。","使君停五马，行乐此中偏。"]},{"id":"t5-664","title":"同和咏楼前海石榴二首 一","rhythmic":null,"author":"孙逖","authorSlug":"孙逖","dynasty":"唐","kind":"shi","paragraphs":["客自新亭郡，朝来数物华。","传君妓楼好，初落海榴花。","露色珠帘映，香风粉壁遮。","更宜林下雨，日晚逐行车。"]},{"id":"t5-665","title":"同和咏楼前海石榴二首 二","rhythmic":null,"author":"孙逖","authorSlug":"孙逖","dynasty":"唐","kind":"shi","paragraphs":["海上移珍木，楼前咏所思。","遥闻下车日，正在落花时。","旧绿香行盖，新红洒步綦。","从来寒不易，终见久逾滋。"]},{"id":"t5-666","title":"故右丞相赠太师燕文贞公挽词二首 一","rhythmic":null,"author":"孙逖","authorSlug":"孙逖","dynasty":"唐","kind":"shi","paragraphs":["海内文章伯，朝端礼乐英。","一言兴宝运，三入济群生。","命与才相偶，年将位不并。","台星忽已坼，流恸轸皇情。"]},{"id":"t5-667","title":"故右丞相赠太师燕文贞公挽词二首 二","rhythmic":null,"author":"孙逖","authorSlug":"孙逖","dynasty":"唐","kind":"shi","paragraphs":["甲第三重戟，高门四列侯。","已成冠盖里，更有凤皇楼。","人世方为乐，生涯遽若休。","空余掌纶地，传庆百千秋。"]},{"id":"t5-668","title":"故陈州刺史赠兵部尚书韦公挽词","rhythmic":null,"author":"孙逖","authorSlug":"孙逖","dynasty":"唐","kind":"shi","paragraphs":["奕叶金章贵，连枝鼎位尊。","台庭为凤穴，相府是鸰原。","世阅空悲命，泉幽不返魂。","惟余汉臣史，继术赞韦门。"]},{"id":"t5-669","title":"故程将军妻南阳郡夫人樊氏挽歌","rhythmic":null,"author":"孙逖","authorSlug":"孙逖","dynasty":"唐","kind":"shi","paragraphs":["德配程休甫，名高鲁季姜。","宠荣苍玉珮，宴梦郁金堂。","白日期偕老，幽泉忽悼亡。","国风犹在咏，江汉近南阳。"]},{"id":"t5-670","title":"和上巳连寒食有怀京洛","rhythmic":null,"author":"孙逖","authorSlug":"孙逖","dynasty":"唐","kind":"shi","paragraphs":["天津御柳碧遥遥，轩骑相从半下朝。","行乐光辉寒食借，太平歌舞晚春饶。","红妆楼下东郊道，青草洲边南渡桥。","坐见司空扫西第，看君侍从落花朝。"]},{"id":"t5-671","title":"和左司张员外自洛使入京中路先赴长安逢立春日赠韦侍御等诸公","rhythmic":null,"author":"孙逖","authorSlug":"孙逖","dynasty":"唐","kind":"shi","paragraphs":["忽覩云间数鴈回，更逢山上正花开。","河边淑气迎芳草，林下轻风待落梅。","秋宪府中高唱入，春卿署里和歌来。","共言东阁招贤地，自有西征谢傅才。"]},{"id":"t5-672","title":"和崔司马登称心山寺","rhythmic":null,"author":"孙逖","authorSlug":"孙逖","dynasty":"唐","kind":"shi","paragraphs":["郡府乘休日，王城访道初。","觉花迎步履，香草藉行车。","倚阁观无际，寻山坐太虚。","岩空迷禹迹，海静望秦余。","翡翠巢珠网，鹍鸡间绮疏。","地灵资净土，水若护真如。","宝树谁攀折，禅云自卷舒。","晴分五湖势，烟合九夷居。","生灭纷无象，窥临已得鱼。","尝闻宝刀赠，今日奉琼琚。"]},{"id":"t5-673","title":"奉和李右相中书壁画山水","rhythmic":null,"author":"孙逖","authorSlug":"孙逖","dynasty":"唐","kind":"shi","paragraphs":["庙堂多暇日，山水契中情。","欲写高深趣，还因藻绘成。","九江临户牖，三峡绕檐楹。","花柳穷年发，烟云逐意生。","能令万里近，不觉四时行。","气染荀香馥，光含乐镜清。","咏歌齐出处，图画表冲盈。","自保千年遇，何论八载荣。"]},{"id":"t5-674","title":"奉和李右相赏会昌林亭","rhythmic":null,"author":"孙逖","authorSlug":"孙逖","dynasty":"唐","kind":"shi","paragraphs":["贤相初陪跸，灵山本降神。","作京雄近县，开阁宠平津。","地胜林亭好，时清宴赏频。","百泉萦草木，万井布郊畛。","德与春和盛，功将造化邻。","还嗤渭滨叟，岁晚独垂纶。"]},{"id":"t5-675","title":"和左衞武仓曹衞中对雨创韵赠右衞李骑曹","rhythmic":null,"author":"孙逖","authorSlug":"孙逖","dynasty":"唐","kind":"shi","paragraphs":["林父同官意，宣尼久敬交。","文场刊玉篆，武事掌金铙。","道合宜连茹，时清岂系匏。","克勤居簿领，多暇屏讙譊。","美酒怀公䜩，玄谈俟客嘲。","薄云生北阙，飞雨自西郊。","院暑便清旷，庭芜觉渐苞。","高门关讵闭，逸韵柱难胶。","枳棘鸾无叹，椅梧凤必巢。","忽闻征竝作，观海媿堂坳。"]},{"id":"t5-676","title":"送新罗法师还国","rhythmic":null,"author":"孙逖","authorSlug":"孙逖","dynasty":"唐","kind":"shi","paragraphs":["异域今无外，高僧代所稀。","苦心归寂灭，宴坐得精微。","持钵何年至，传灯是日归。","上卿挥别藻，中禁下禅衣。","海阔杯还度，云遥锡更飞。","此行迷处所，何以慰虔祈。"]},{"id":"t5-677","title":"送赵大夫护边","rhythmic":null,"author":"孙逖","authorSlug":"孙逖","dynasty":"唐","kind":"shi","paragraphs":["外域分都护，中台命职方。","欲传清庙略，先取剧曹郎。","已佩登坛印，犹怀伏奏香。","百壶开祖饯，驷牡戒戎装。","青海连西掖，黄河带北凉。","关山瞻汉月，戈劒宿胡霜。","体国才先著，论兵策复长。","果持文武术，还继杜当阳。"]},{"id":"t5-678","title":"立秋日题安昌寺北山亭","rhythmic":null,"author":"孙逖","authorSlug":"孙逖","dynasty":"唐","kind":"shi","paragraphs":["楼观倚长霄，登攀及霁朝。","高如石门顶，胜拟赤城标。","天路云虹近，人寰气象遥。","山围伯禹庙，江落伍胥潮。","徂暑迎秋薄，凉风是日飘。","果林余苦李，萍水覆甘蕉。","览古嗟夷漫，凌空爱泬寥。","更闻金刹下，钟梵晚萧萧。"]},{"id":"t5-679","title":"登越州城","rhythmic":null,"author":"孙逖","authorSlug":"孙逖","dynasty":"唐","kind":"shi","paragraphs":["越嶂绕层城，登临万象清。","封圻沧海合，廛市碧湖明。","晓日渔歌满，芳春櫂唱行。","山风吹美箭，田雨润香秔。","代阅英灵尽，人闲吏隐并。","赠言王逸少，已见曲池平。"]},{"id":"t5-680","title":"江行有怀","rhythmic":null,"author":"孙逖","authorSlug":"孙逖","dynasty":"唐","kind":"shi","paragraphs":["秋水明川路，轻舟转石圻。","霜多山橘熟，寒至浦禽稀。","飞席乘风势，回流荡日晖。","昼行疑海若，夕梦识江妃。","野霁看吴尽，天长望洛非。","不知何岁月，一似暮潮归。"]},{"id":"t5-681","title":"长洲苑","rhythmic":null,"author":"孙逖","authorSlug":"孙逖","dynasty":"唐","kind":"shi","paragraphs":["吴王初鼎峙，羽猎骋雄才。","辇道阊门出，军容茂苑来。","山从列嶂转，江自绕林回。","劒骑缘汀入，旌门隔屿开。","合离纷若电，驰逐溢成雷。","胜地虞人守，归舟汉女陪。","可怜夷漫处，犹在洞庭隈。","山静吟猿父，城空应雉媒。","戎行委乔木，马迹尽黄埃。","揽涕问遗老，繁华安在哉。"]},{"id":"t5-682","title":"和咏廨署有樱桃","rhythmic":null,"author":"孙逖","authorSlug":"孙逖","dynasty":"唐","kind":"shi","paragraphs":["上林天禁里，芳树有红樱。","江国今来见，君门春意生。","香从花绶转，色绕佩珠明。","海鸟衔初实，吴姬扫落英。","切将稀取贵，羞与众同荣。","为此堪攀折，芳蹊处处成。"]},{"id":"t5-683","title":"同洛阳李少府观永乐公主入蕃","rhythmic":null,"author":"孙逖","authorSlug":"孙逖","dynasty":"唐","kind":"shi","paragraphs":["边地莺花少，年来未觉新。","美人天上落，龙塞始应春。"]},{"id":"t5-684","title":"途中口号","rhythmic":null,"author":"孙逖","authorSlug":"孙逖","dynasty":"唐","kind":"shi","paragraphs":["邺城东北望陵台，珠翠繁华去不回。","无复新妆艳红粉，空余故垄满青苔。"]},{"id":"t5-685","title":"晦日湖塘","rhythmic":null,"author":"孙逖","authorSlug":"孙逖","dynasty":"唐","kind":"shi","paragraphs":["吉日初成晦，方塘遍是春。","落花迎二月，芳树历三旬。","公子能留客，巫阳好解神。","夜还何虑暗，秉烛向城𬮱。"]},{"id":"t5-686","title":"句","rhythmic":null,"author":"孙逖","authorSlug":"孙逖","dynasty":"唐","kind":"shi","paragraphs":["野烟出炉上，山花落镜中。"]},{"id":"t5-687","title":"从军行","rhythmic":null,"author":"崔国辅","authorSlug":"崔国辅","dynasty":"唐","kind":"shi","paragraphs":["塞北胡霜下，营州索兵救。","夜里偷道行，将军马亦瘦。","刀光照塞月，阵色明如昼。","传闻贼满山，已共前锋鬬。"]},{"id":"t5-688","title":"杂诗","rhythmic":null,"author":"崔国辅","authorSlug":"崔国辅","dynasty":"唐","kind":"shi","paragraphs":["逢著平乐儿，论交鞍马前。","与酤一斗酒，恰用十千钱。","后余在关内，作事多迍邅。","何肯相救援，徒闻宝劒篇。"]},{"id":"t5-689","title":"古意","rhythmic":null,"author":"崔国辅","authorSlug":"崔国辅","dynasty":"唐","kind":"shi","paragraphs":["红荷楚水曲，彪炳烁晨霞。","未得两回摘，秋风吹却花。","时芳不待妾，玉珮无处夸。","悔不盛年时，嫁与青楼家。"]},{"id":"t5-690","title":"宿法华寺","rhythmic":null,"author":"崔国辅","authorSlug":"崔国辅","dynasty":"唐","kind":"shi","paragraphs":["松雨时复滴，寺门清且凉。","此心竟谁证，回憩支公床。","壁画感灵迹，龛经传异香。","独游寄象外，忽忽归南昌。"]},{"id":"t5-691","title":"题豫章馆","rhythmic":null,"author":"崔国辅","authorSlug":"崔国辅","dynasty":"唐","kind":"shi","paragraphs":["杨柳映春江，江南转佳丽。","吴门绿波里，越国青山际。","游宦常往来，津亭暂临憩。","驿前苍石没，浦外湖沙细。","向晚宴且久，孤舟冏然逝。","云留西北客，气歇东南帝。","独有萋萋心，谁知怨芳岁。"]},{"id":"t5-692","title":"石头滩作","rhythmic":null,"author":"崔国辅","authorSlug":"崔国辅","dynasty":"唐","kind":"shi","paragraphs":["怅矣秋风时，余临石头濑。","因高见远境，尽此数州内。","羽山数点青，海岸杂光碎。","离离树木少，漭漭湖波大。","日暮千里帆，南飞落天外。","须臾遂入夜，楚色有微霭。","寻远迹已穷，遗荣事多昧。","一身犹未理，安得济时代。","且泛朝夕潮，荷衣蕙为带。"]},{"id":"t5-693","title":"漂母岸","rhythmic":null,"author":"崔国辅","authorSlug":"崔国辅","dynasty":"唐","kind":"shi","paragraphs":["泗水入淮处，南边古岸存。","秦时有漂母，于此饭王孙。","王孙初未遇，寄食何足论。","后为楚王来，黄金答母恩。","事迹遗在此，空伤千载魂。","茫茫水中渚，上有一孤墩。","遥望不可到，苍苍烟树昏。","几年崩冢色，每日落潮痕。","古地多陻圮，时哉不敢言。","向夕泪沾裳，遂宿芦洲村。"]},{"id":"t5-694","title":"对酒吟","rhythmic":null,"author":"崔国辅","authorSlug":"崔国辅","dynasty":"唐","kind":"shi","paragraphs":["行行日将夕，荒村古冢无人迹。","蒙笼荆棘一鸟吟，屡唱提壶沽酒吃。","古人不达酒不足，遗恨精灵传此曲。","寄言世上诸少年，平生且尽杯中醁。"]},{"id":"t5-695","title":"奉和华清宫观行香应制","rhythmic":null,"author":"崔国辅","authorSlug":"崔国辅","dynasty":"唐","kind":"shi","paragraphs":["天子蘂珠宫，楼台碧落通。","豫游皆汗漫，斋处即崆峒。","云物三光里，君臣一气中。","道言何所说，宝历自无穷。"]},{"id":"t5-696","title":"七夕","rhythmic":null,"author":"崔国辅","authorSlug":"崔国辅","dynasty":"唐","kind":"shi","paragraphs":["太守仙潢族，含情七夕多。","扇风生玉漏，置水写银河。","阁下陈书籍，闺中曝绮罗。","遥思汉武帝，青鸟几时过。"]},{"id":"t5-697","title":"宿范浦","rhythmic":null,"author":"崔国辅","authorSlug":"崔国辅","dynasty":"唐","kind":"shi","paragraphs":["月暗潮又落，西陵渡暂停。","村烟和海雾，舟火乱江星。","路转定山遶，塘连范浦横。","鸱夷近何去，空山临沧溟。"]},{"id":"t5-698","title":"奉和圣制上巳祓禊应制","rhythmic":null,"author":"崔国辅","authorSlug":"崔国辅","dynasty":"唐","kind":"shi","paragraphs":["元巳秦中节，吾君灞上游。","鸣銮通禁苑，别馆遶芳洲。","鹓鹭千官列，鱼龙百戏浮。","桃花春欲尽，谷雨夜来收。","庆向尧樽祝，欢从楚棹讴。","逸诗何足对，窅作掩东周。"]},{"id":"t5-699","title":"九日侍宴应制","rhythmic":null,"author":"崔国辅","authorSlug":"崔国辅","dynasty":"唐","kind":"shi","paragraphs":["运偶千年圣，时传九日神。","尧樽列钟鼓，汉阙辟钩陈。","金箓三清降，琼筵五老巡。","始惊兰佩出，复咏柏梁新。","云鴈楼前晚，霜花酒里春。","欢娱无限极，书劒太平人。"]}]